{"0":{"wrapper":{"fluid":true,"css":{"border":"0","backgroundColor":"#FFFFFF"},"rows":[{"css":{"padding":"0","border":"0"},"columns":{"sizes":["col-md-12"]}}]},"rows":[{"columns":[{"items":[{"src":"https://code.rateparity.com/aquavistahotels.com/2022/12/Portara.jpeg","alt":"alt hotel image"},{"src":"https://code.rateparity.com/aquavistahotels.com/2022/12/Portara-4.jpeg","alt":"alt hotel image"},{"src":"https://code.rateparity.com/aquavistahotels.com/2022/12/Portara-6.jpeg","alt":"alt hotel image"},{"src":"https://code.rateparity.com/aquavistahotels.com/2022/12/Portara-10.jpeg","alt":"alt hotel image"}],"heading":"Villa Portara","css":{"heading":{"element":"div","class":"title-case-hero text-uppercase","color":"primary-white"}}}]}]},"1":{"wrapper":{"fluid":false,"css":{"border":"0","backgroundColor":"#FFFFFF"},"class":"d-none d-md-block","rows":[{"css":{"padding":"80px 0 0 0","border":"0"},"columns":{"sizes":["col-md-12 animation--up"]}}]},"rows":[{"columns":[{"items":[{"link":"/","label":"AQUA VISTA HOTELS"},{"link":"/hotels-in-naxos/apricot-sea-luxury-villas-naxos","label":"apricot sea luxury-villas-naxos"},{"link":"/hotels-in-naxos/apricot-sea-luxury-villas-naxos/rooms","label":"rooms"},{"link":"","label":"villa portara"}],"css":{"element":"div","class":"secondary-post-text","color":"primary-dark"}}]}]},"2":{"wrapper":{"fluid":true,"css":{"border":"0","backgroundColor":"#FFFFFF"},"rows":[{"css":{},"columns":{"sizes":["col-md-12 no-transform animation--up"]}}]},"rows":[{"columns":[{"menu":[{"link":"/hotels-in-naxos/apricot-sea-luxury-villas-naxos","label":"hotel","active":false},{"link":"/hotels-in-naxos/apricot-sea-luxury-villas-naxos/rooms","label":"rooms","active":true},{"link":"/hotels-in-naxos/apricot-sea-luxury-villas-naxos/location","label":"location","active":false},{"link":"/hotels-in-naxos/apricot-sea-luxury-villas-naxos/facilities","label":"facilities","active":false}],"link":{"pathname":"/dreams-luxury-suites","api":"/pages/room/room1"},"css":{"element":"div"}}]}]},"3":{"wrapper":{"fluid":false,"css":{"border":"0","backgroundColor":"#FFFFFF"},"rows":[{"css":{"padding":"200px 0 0 0","border":"0"},"columns":{"sizes":["col-md-12 animation--up","col-md-12 animation--up","col-md-12 animation--up"]}}]},"rows":[{"columns":[{"text":"Villa Portara","css":{"element":"div","class":"animation--up title-case-primary p-b-20","color":"primary-black"}},{"text":"<p><span style=\"font-weight: 400;\">Villa Portara, which took its name from the most famous monument of Naxos, will thrill you with its gorgeous views and it will spoil you with direct access to the swimming pool, the barbecue and the outdoor comfortable and luxurious seating areas. </span></p>\n<p><span style=\"font-weight: 400;\">Don’t hesitate to look in the cupboards for whatever you need as we have tried to provide a maximum of supplies for you. Reserve villa Portara for families or groups of up to 7 visitors.</span></p>\n<p><span style=\"font-weight: 400;\">Room total:85 sq.m</span></p>\n","css":{"element":"div","class":"animation--up main-text-body","color":"primary-black "}},{"text":"<div\n             class=\"d-flex justify-content-between align-items-center\">\n              <span\n            class=\"secondary-blue\" >Up to 7 Guests/ sea view</span><br>\n            <a class=\"\" href=\"https://apricotandsea.reserve-online.net/\">\n                <button class=\"button-fill\">BOOK NOW</button>\n            </a>\n        </div>","css":{"element":"div","class":"animation--up main-text-body","color":"primary-black"}}]}]},"4":{"wrapper":{"fluid":false,"css":{"border":"0","backgroundColor":"#FFFFFF"},"rows":[{"css":{"padding":"0 0 60px 0","border":"0","margin":"0 auto"},"columns":{"sizes":["col-md-12 p-0 animation--up","col-md-12 p-0 animation--up","col-md-12 p-0 px-3 px-sm-0 animation--up"]}}]},"rows":[{"columns":[{"maxWidth":"100%","color":"#04456D","padding":"40px","margin":"0 auto"},{"text":"Amenities","css":{"element":"div","class":"title-case-primary text-left p-b-20 animation--up","color":"primary-dark "}},{"text":"<ul class=\"three-col\">\n<li style=\"font-weight: 400;\" aria-level=\"1\"><span style=\"font-weight: 400;\">Cleaning every day</span></li>\n<li style=\"font-weight: 400;\" aria-level=\"1\"><span style=\"font-weight: 400;\">Bed sheets change every 2 days</span></li>\n<li style=\"font-weight: 400;\" aria-level=\"1\"><span style=\"font-weight: 400;\">Free wifi</span></li>\n<li style=\"font-weight: 400;\" aria-level=\"1\"><span style=\"font-weight: 400;\">Flat-screen satellite tv</span></li>\n<li style=\"font-weight: 400;\" aria-level=\"1\"><span style=\"font-weight: 400;\">Air conditioning</span></li>\n<li style=\"font-weight: 400;\" aria-level=\"1\"><span style=\"font-weight: 400;\">Full kitchen cooking equipment</span></li>\n<li style=\"font-weight: 400;\" aria-level=\"1\"><span style=\"font-weight: 400;\">Dish washer</span></li>\n<li style=\"font-weight: 400;\" aria-level=\"1\"><span style=\"font-weight: 400;\">Oven</span></li>\n<li style=\"font-weight: 400;\" aria-level=\"1\"><span style=\"font-weight: 400;\">Microwave</span></li>\n<li style=\"font-weight: 400;\" aria-level=\"1\"><span style=\"font-weight: 400;\">Coffee machine</span></li>\n<li style=\"font-weight: 400;\" aria-level=\"1\"><span style=\"font-weight: 400;\">Fridge</span></li>\n<li style=\"font-weight: 400;\" aria-level=\"1\"><span style=\"font-weight: 400;\">Washing machine</span></li>\n<li style=\"font-weight: 400;\" aria-level=\"1\"><span style=\"font-weight: 400;\">Iron with iron board</span></li>\n<li style=\"font-weight: 400;\" aria-level=\"1\"><span style=\"font-weight: 400;\">Bathroom and pool towels</span></li>\n<li style=\"font-weight: 400;\" aria-level=\"1\"><span style=\"font-weight: 400;\">Dryer</span></li>\n<li style=\"font-weight: 400;\" aria-level=\"1\"><span style=\"font-weight: 400;\">Fireplace</span></li>\n<li style=\"font-weight: 400;\" aria-level=\"1\"><span style=\"font-weight: 400;\">Safe Box</span></li>\n<li style=\"font-weight: 400;\" aria-level=\"1\"><span style=\"font-weight: 400;\">Swimming pool</span></li>\n<li style=\"font-weight: 400;\" aria-level=\"1\"><span style=\"font-weight: 400;\">Barbecue</span></li>\n<li style=\"font-weight: 400;\" aria-level=\"1\"><span style=\"font-weight: 400;\">Outside seating space with pool and sea view</span></li>\n<li style=\"font-weight: 400;\" aria-level=\"1\"><span style=\"font-weight: 400;\">Parking</span></li>\n<li style=\"font-weight: 400;\" aria-level=\"1\"><span style=\"font-weight: 400;\">Storage space</span></li>\n</ul>\n","icon":"/public/hotels/acquavista/svg/Plus.svg","css":{"element":"div","class":"main-text-body animation--up","color":"primary-black"}}]}]},"5":{"wrapper":{"fluid":true,"css":{"border":"0","backgroundColor":"#04456D"},"rows":[{"css":{"padding":"80px 0 60px 0","border":"0","maxWidth":"1440px","margin":"0 auto"},"columns":{"sizes":["col-md-12 py-5 animation--up"]}}]},"rows":[{"columns":[{"items":[{"src":"https://code.rateparity.com/aquavistahotels.com/2022/12/Portara.jpeg","alt":"alt images"},{"src":"https://code.rateparity.com/aquavistahotels.com/2022/12/Portara-2.jpeg","alt":"alt images"},{"src":"https://code.rateparity.com/aquavistahotels.com/2022/12/Portara-4.jpeg","alt":"alt images"},{"src":"https://code.rateparity.com/aquavistahotels.com/2022/12/Portara-5.jpeg","alt":"alt images"},{"src":"https://code.rateparity.com/aquavistahotels.com/2022/12/Portara-6.jpeg","alt":"alt images"},{"src":"https://code.rateparity.com/aquavistahotels.com/2022/12/Portara-3.jpeg","alt":"alt images"},{"src":"https://code.rateparity.com/aquavistahotels.com/2022/12/Portara-9.jpeg","alt":"alt images"},{"src":"https://code.rateparity.com/aquavistahotels.com/2022/12/Portara-10.jpeg","alt":"alt images"},{"src":"https://code.rateparity.com/aquavistahotels.com/2022/12/Portara-8.jpeg","alt":"alt images"},{"src":"https://code.rateparity.com/aquavistahotels.com/2022/12/Portara-7.jpeg","alt":"alt images"}],"css":{}}]}]},"6":{"wrapper":{"fluid":true,"css":{"border":"0","backgroundColor":"#FFFFFF"},"rows":[{"css":{"padding":"80px 0 60px 0","border":"0","maxWidth":"1440px","margin":"0 auto"},"columns":{"sizes":["col-md-12 animation--up"]}},{"css":{"padding":"0 0 60px 0","border":"0","maxWidth":"1440px","margin":"0 auto"},"columns":{"sizes":["col-md-12  animation--up"]}}]},"rows":[{"columns":[{"text":"Explore more rooms","link":{"pathname":"/hotels-in-naxos/apricot-sea-luxury-villas-naxos/rooms","api":"/pages/room/room1"},"css":{"element":"div","class":"title-case-primary text-uppercase text-center animation--up","color":"primary-dark","maxWidth":"512px","margin":"0 auto","padding":"0 0 0 0"}}]},{"columns":[{"link":{"pathname":"/hotels-in-naxos/apricot-sea-luxury-villas-naxos/rooms","api":"/pages/room/room1","text":"Explore"},"items":[{"description":"One of the Top 2 most spacious residences of Apricot & Sea, Maisonette Emery with its 110 square meters provides you with all the space you need in order to enjoy your vacation in full comfort.","title":"Maisonette Villa Emery","slider_gallery":[{"ID":2193,"id":2193,"title":"Emery-2","filename":"Emery-2.jpeg","filesize":168447,"url":"https://greece-hotel.info/admins/aquavistahotels/wp-content/uploads/2022/12/Emery-2.jpeg","link":"https://greece-hotel.info/admins/aquavistahotels/hotelss/apricot-sea-luxury-villas-naxos/emery-2/","alt":"","author":"1","description":"","caption":"","name":"emery-2","status":"inherit","uploaded_to":2183,"date":"2022-12-08 08:24:25","modified":"2022-12-08 09:55:10","menu_order":0,"mime_type":"image/jpeg","type":"image","subtype":"jpeg","icon":"https://greece-hotel.info/admins/aquavistahotels/wp-includes/images/media/default.png","width":1920,"height":1280,"sizes":{"thumbnail":"https://greece-hotel.info/admins/aquavistahotels/wp-content/uploads/2022/12/Emery-2-150x150.jpeg","thumbnail-width":150,"thumbnail-height":150,"medium":"https://greece-hotel.info/admins/aquavistahotels/wp-content/uploads/2022/12/Emery-2-300x200.jpeg","medium-width":300,"medium-height":200,"medium_large":"https://greece-hotel.info/admins/aquavistahotels/wp-content/uploads/2022/12/Emery-2-768x512.jpeg","medium_large-width":768,"medium_large-height":512,"large":"https://greece-hotel.info/admins/aquavistahotels/wp-content/uploads/2022/12/Emery-2-1024x683.jpeg","large-width":1024,"large-height":683,"1536x1536":"https://greece-hotel.info/admins/aquavistahotels/wp-content/uploads/2022/12/Emery-2-1536x1024.jpeg","1536x1536-width":1536,"1536x1536-height":1024,"2048x2048":"https://greece-hotel.info/admins/aquavistahotels/wp-content/uploads/2022/12/Emery-2.jpeg","2048x2048-width":1920,"2048x2048-height":1280,"hotels-thumb":"https://greece-hotel.info/admins/aquavistahotels/wp-content/uploads/2022/12/Emery-2-260x173.jpeg","hotels-thumb-width":260,"hotels-thumb-height":173}},{"ID":2190,"id":2190,"title":"Emery-8","filename":"Emery-8.jpeg","filesize":271539,"url":"https://greece-hotel.info/admins/aquavistahotels/wp-content/uploads/2022/12/Emery-8.jpeg","link":"https://greece-hotel.info/admins/aquavistahotels/hotelss/apricot-sea-luxury-villas-naxos/emery-8/","alt":"","author":"1","description":"","caption":"","name":"emery-8","status":"inherit","uploaded_to":2183,"date":"2022-12-08 08:24:19","modified":"2022-12-08 08:24:19","menu_order":0,"mime_type":"image/jpeg","type":"image","subtype":"jpeg","icon":"https://greece-hotel.info/admins/aquavistahotels/wp-includes/images/media/default.png","width":1920,"height":1280,"sizes":{"thumbnail":"https://greece-hotel.info/admins/aquavistahotels/wp-content/uploads/2022/12/Emery-8-150x150.jpeg","thumbnail-width":150,"thumbnail-height":150,"medium":"https://greece-hotel.info/admins/aquavistahotels/wp-content/uploads/2022/12/Emery-8-300x200.jpeg","medium-width":300,"medium-height":200,"medium_large":"https://greece-hotel.info/admins/aquavistahotels/wp-content/uploads/2022/12/Emery-8-768x512.jpeg","medium_large-width":768,"medium_large-height":512,"large":"https://greece-hotel.info/admins/aquavistahotels/wp-content/uploads/2022/12/Emery-8-1024x683.jpeg","large-width":1024,"large-height":683,"1536x1536":"https://greece-hotel.info/admins/aquavistahotels/wp-content/uploads/2022/12/Emery-8-1536x1024.jpeg","1536x1536-width":1536,"1536x1536-height":1024,"2048x2048":"https://greece-hotel.info/admins/aquavistahotels/wp-content/uploads/2022/12/Emery-8.jpeg","2048x2048-width":1920,"2048x2048-height":1280,"hotels-thumb":"https://greece-hotel.info/admins/aquavistahotels/wp-content/uploads/2022/12/Emery-8-260x173.jpeg","hotels-thumb-width":260,"hotels-thumb-height":173}},{"ID":2188,"id":2188,"title":"Emery-6","filename":"Emery-6.jpeg","filesize":385664,"url":"https://greece-hotel.info/admins/aquavistahotels/wp-content/uploads/2022/12/Emery-6.jpeg","link":"https://greece-hotel.info/admins/aquavistahotels/hotelss/apricot-sea-luxury-villas-naxos/emery-6/","alt":"","author":"1","description":"","caption":"","name":"emery-6","status":"inherit","uploaded_to":2183,"date":"2022-12-08 08:24:16","modified":"2022-12-08 08:24:16","menu_order":0,"mime_type":"image/jpeg","type":"image","subtype":"jpeg","icon":"https://greece-hotel.info/admins/aquavistahotels/wp-includes/images/media/default.png","width":1920,"height":1280,"sizes":{"thumbnail":"https://greece-hotel.info/admins/aquavistahotels/wp-content/uploads/2022/12/Emery-6-150x150.jpeg","thumbnail-width":150,"thumbnail-height":150,"medium":"https://greece-hotel.info/admins/aquavistahotels/wp-content/uploads/2022/12/Emery-6-300x200.jpeg","medium-width":300,"medium-height":200,"medium_large":"https://greece-hotel.info/admins/aquavistahotels/wp-content/uploads/2022/12/Emery-6-768x512.jpeg","medium_large-width":768,"medium_large-height":512,"large":"https://greece-hotel.info/admins/aquavistahotels/wp-content/uploads/2022/12/Emery-6-1024x683.jpeg","large-width":1024,"large-height":683,"1536x1536":"https://greece-hotel.info/admins/aquavistahotels/wp-content/uploads/2022/12/Emery-6-1536x1024.jpeg","1536x1536-width":1536,"1536x1536-height":1024,"2048x2048":"https://greece-hotel.info/admins/aquavistahotels/wp-content/uploads/2022/12/Emery-6.jpeg","2048x2048-width":1920,"2048x2048-height":1280,"hotels-thumb":"https://greece-hotel.info/admins/aquavistahotels/wp-content/uploads/2022/12/Emery-6-260x173.jpeg","hotels-thumb-width":260,"hotels-thumb-height":173}},{"ID":2186,"id":2186,"title":"Emery-4","filename":"Emery-4.jpeg","filesize":405890,"url":"https://greece-hotel.info/admins/aquavistahotels/wp-content/uploads/2022/12/Emery-4.jpeg","link":"https://greece-hotel.info/admins/aquavistahotels/hotelss/apricot-sea-luxury-villas-naxos/emery-4/","alt":"","author":"1","description":"","caption":"","name":"emery-4","status":"inherit","uploaded_to":2183,"date":"2022-12-08 08:24:13","modified":"2022-12-08 08:24:13","menu_order":0,"mime_type":"image/jpeg","type":"image","subtype":"jpeg","icon":"https://greece-hotel.info/admins/aquavistahotels/wp-includes/images/media/default.png","width":1920,"height":1280,"sizes":{"thumbnail":"https://greece-hotel.info/admins/aquavistahotels/wp-content/uploads/2022/12/Emery-4-150x150.jpeg","thumbnail-width":150,"thumbnail-height":150,"medium":"https://greece-hotel.info/admins/aquavistahotels/wp-content/uploads/2022/12/Emery-4-300x200.jpeg","medium-width":300,"medium-height":200,"medium_large":"https://greece-hotel.info/admins/aquavistahotels/wp-content/uploads/2022/12/Emery-4-768x512.jpeg","medium_large-width":768,"medium_large-height":512,"large":"https://greece-hotel.info/admins/aquavistahotels/wp-content/uploads/2022/12/Emery-4-1024x683.jpeg","large-width":1024,"large-height":683,"1536x1536":"https://greece-hotel.info/admins/aquavistahotels/wp-content/uploads/2022/12/Emery-4-1536x1024.jpeg","1536x1536-width":1536,"1536x1536-height":1024,"2048x2048":"https://greece-hotel.info/admins/aquavistahotels/wp-content/uploads/2022/12/Emery-4.jpeg","2048x2048-width":1920,"2048x2048-height":1280,"hotels-thumb":"https://greece-hotel.info/admins/aquavistahotels/wp-content/uploads/2022/12/Emery-4-260x173.jpeg","hotels-thumb-width":260,"hotels-thumb-height":173}}],"intro_text":"Maisonette Villa Emery","book_now":"https://apricotandsea.reserve-online.net/","image":{"src":"https://code.rateparity.com/aquavistahotels.com/2022/12/Emery-6.jpeg","alt":"alt image"},"excerpt":"One of the Top 2 most spacious residences of Apricot & Sea, Maisonette Emery with its 110 square meters provides you with all the space you need in order to enjoy your vacation in full comfort.","amenities":"<ul class=\"three-col\">\n<li style=\"font-weight: 400;\" aria-level=\"1\"><span style=\"font-weight: 400;\">Cleaning every day</span></li>\n<li style=\"font-weight: 400;\" aria-level=\"1\"><span style=\"font-weight: 400;\">Bed sheets change every 2 days</span></li>\n<li style=\"font-weight: 400;\" aria-level=\"1\"><span style=\"font-weight: 400;\">Free wifi</span></li>\n<li style=\"font-weight: 400;\" aria-level=\"1\"><span style=\"font-weight: 400;\">Flat-screen satellite tv</span></li>\n<li style=\"font-weight: 400;\" aria-level=\"1\"><span style=\"font-weight: 400;\">Air conditioning</span></li>\n<li style=\"font-weight: 400;\" aria-level=\"1\"><span style=\"font-weight: 400;\">Full kitchen cooking equipment</span></li>\n<li style=\"font-weight: 400;\" aria-level=\"1\"><span style=\"font-weight: 400;\">Dish washer</span></li>\n<li style=\"font-weight: 400;\" aria-level=\"1\"><span style=\"font-weight: 400;\">Oven</span></li>\n<li style=\"font-weight: 400;\" aria-level=\"1\"><span style=\"font-weight: 400;\">Microwave</span></li>\n<li style=\"font-weight: 400;\" aria-level=\"1\"><span style=\"font-weight: 400;\">Coffee machine</span></li>\n<li style=\"font-weight: 400;\" aria-level=\"1\"><span style=\"font-weight: 400;\">Fridge</span></li>\n<li style=\"font-weight: 400;\" aria-level=\"1\"><span style=\"font-weight: 400;\">Washing machine</span></li>\n<li style=\"font-weight: 400;\" aria-level=\"1\"><span style=\"font-weight: 400;\">Iron with iron board</span></li>\n<li style=\"font-weight: 400;\" aria-level=\"1\"><span style=\"font-weight: 400;\">Bathroom and pool towels</span></li>\n<li style=\"font-weight: 400;\" aria-level=\"1\"><span style=\"font-weight: 400;\">Dryer</span></li>\n<li style=\"font-weight: 400;\" aria-level=\"1\"><span style=\"font-weight: 400;\">Fireplace</span></li>\n<li style=\"font-weight: 400;\" aria-level=\"1\"><span style=\"font-weight: 400;\">Safe box</span></li>\n<li style=\"font-weight: 400;\" aria-level=\"1\"><span style=\"font-weight: 400;\">Swimming pool</span></li>\n<li style=\"font-weight: 400;\" aria-level=\"1\"><span style=\"font-weight: 400;\">Barbecue</span></li>\n<li style=\"font-weight: 400;\" aria-level=\"1\"><span style=\"font-weight: 400;\">Outside seating space with pool and sea view</span></li>\n<li style=\"font-weight: 400;\" aria-level=\"1\"><span style=\"font-weight: 400;\">Parking</span></li>\n<li style=\"font-weight: 400;\" aria-level=\"1\"><span style=\"font-weight: 400;\">Storage space</span></li>\n</ul>\n","amenities_with_icons":[{"icon":"https://code.rateparity.com/aquavistahotels.com/2022/09/icon-3-1.svg","name":"ADSL Internet Connection"},{"icon":"https://code.rateparity.com/aquavistahotels.com/2022/07/007-fan.svg","name":"Air Conditioning"},{"icon":"https://code.rateparity.com/aquavistahotels.com/2022/07/handshake.svg","name":"Business Lounge"},{"icon":"https://code.rateparity.com/aquavistahotels.com/2022/07/bar.svg","name":"Bar"}],"gallery":["https://greece-hotel.info/admins/aquavistahotels/wp-content/uploads/2022/12/Emery-2.jpeg","https://greece-hotel.info/admins/aquavistahotels/wp-content/uploads/2022/12/Emery.jpeg","https://greece-hotel.info/admins/aquavistahotels/wp-content/uploads/2022/12/Emery-7.jpeg","https://greece-hotel.info/admins/aquavistahotels/wp-content/uploads/2022/12/Emery-8.jpeg","https://greece-hotel.info/admins/aquavistahotels/wp-content/uploads/2022/12/Emery-3.jpeg","https://greece-hotel.info/admins/aquavistahotels/wp-content/uploads/2022/12/Emery-5.jpeg","https://greece-hotel.info/admins/aquavistahotels/wp-content/uploads/2022/12/Emery-6.jpeg","https://greece-hotel.info/admins/aquavistahotels/wp-content/uploads/2022/12/Emery-4.jpeg","https://greece-hotel.info/admins/aquavistahotels/wp-content/uploads/2022/12/Emery-10-scaled.jpeg"],"seo_title":"Maisonette Villa Emery | Apricot & Sea Luxury Villas Naxos","seo_description":"Maisonetter Villa Emery is a charming 110 sq.m space for up to 9 guests. Fully-equipped kitchen. Access to pool & barbecue. Unique sea views. Book now!","keywords":"","small_info":"Up to 9 Guests/ pool and sea view","link":{"pathname":"/hotels-in-naxos/apricot-sea-luxury-villas-naxos/rooms/maisonette-villa-emery","api":"/pages/room/room1","text":"Explore"}},{"description":"One of the Top 2 most spacious residences of Apricot & Sea, maisonette Kitron like the most traditional and well-known drink of Naxos from which it takes its name, gives you the chance...","title":"Maisonette Villa Kitron","slider_gallery":[{"ID":2196,"id":2196,"title":"Kitron-7","filename":"Kitron-7-scaled.jpeg","filesize":523398,"url":"https://greece-hotel.info/admins/aquavistahotels/wp-content/uploads/2022/12/Kitron-7-scaled.jpeg","link":"https://greece-hotel.info/admins/aquavistahotels/hotelss/apricot-sea-luxury-villas-naxos/kitron-7/","alt":"","author":"1","description":"","caption":"","name":"kitron-7","status":"inherit","uploaded_to":2183,"date":"2022-12-08 08:24:44","modified":"2022-12-08 10:11:33","menu_order":0,"mime_type":"image/jpeg","type":"image","subtype":"jpeg","icon":"https://greece-hotel.info/admins/aquavistahotels/wp-includes/images/media/default.png","width":2560,"height":1707,"sizes":{"thumbnail":"https://greece-hotel.info/admins/aquavistahotels/wp-content/uploads/2022/12/Kitron-7-scaled-150x150.jpeg","thumbnail-width":150,"thumbnail-height":150,"medium":"https://greece-hotel.info/admins/aquavistahotels/wp-content/uploads/2022/12/Kitron-7-scaled-300x200.jpeg","medium-width":300,"medium-height":200,"medium_large":"https://greece-hotel.info/admins/aquavistahotels/wp-content/uploads/2022/12/Kitron-7-scaled-768x512.jpeg","medium_large-width":768,"medium_large-height":512,"large":"https://greece-hotel.info/admins/aquavistahotels/wp-content/uploads/2022/12/Kitron-7-scaled-1024x683.jpeg","large-width":1024,"large-height":683,"1536x1536":"https://greece-hotel.info/admins/aquavistahotels/wp-content/uploads/2022/12/Kitron-7-scaled-1536x1024.jpeg","1536x1536-width":1536,"1536x1536-height":1024,"2048x2048":"https://greece-hotel.info/admins/aquavistahotels/wp-content/uploads/2022/12/Kitron-7-scaled-2048x1366.jpeg","2048x2048-width":2048,"2048x2048-height":1366,"hotels-thumb":"https://greece-hotel.info/admins/aquavistahotels/wp-content/uploads/2022/12/Kitron-7-scaled-260x173.jpeg","hotels-thumb-width":260,"hotels-thumb-height":173}},{"ID":2199,"id":2199,"title":"Kitron","filename":"Kitron.jpeg","filesize":163480,"url":"https://greece-hotel.info/admins/aquavistahotels/wp-content/uploads/2022/12/Kitron.jpeg","link":"https://greece-hotel.info/admins/aquavistahotels/hotelss/apricot-sea-luxury-villas-naxos/kitron/","alt":"","author":"1","description":"","caption":"","name":"kitron","status":"inherit","uploaded_to":2183,"date":"2022-12-08 08:24:49","modified":"2022-12-08 08:24:49","menu_order":0,"mime_type":"image/jpeg","type":"image","subtype":"jpeg","icon":"https://greece-hotel.info/admins/aquavistahotels/wp-includes/images/media/default.png","width":1920,"height":1280,"sizes":{"thumbnail":"https://greece-hotel.info/admins/aquavistahotels/wp-content/uploads/2022/12/Kitron-150x150.jpeg","thumbnail-width":150,"thumbnail-height":150,"medium":"https://greece-hotel.info/admins/aquavistahotels/wp-content/uploads/2022/12/Kitron-300x200.jpeg","medium-width":300,"medium-height":200,"medium_large":"https://greece-hotel.info/admins/aquavistahotels/wp-content/uploads/2022/12/Kitron-768x512.jpeg","medium_large-width":768,"medium_large-height":512,"large":"https://greece-hotel.info/admins/aquavistahotels/wp-content/uploads/2022/12/Kitron-1024x683.jpeg","large-width":1024,"large-height":683,"1536x1536":"https://greece-hotel.info/admins/aquavistahotels/wp-content/uploads/2022/12/Kitron-1536x1024.jpeg","1536x1536-width":1536,"1536x1536-height":1024,"2048x2048":"https://greece-hotel.info/admins/aquavistahotels/wp-content/uploads/2022/12/Kitron.jpeg","2048x2048-width":1920,"2048x2048-height":1280,"hotels-thumb":"https://greece-hotel.info/admins/aquavistahotels/wp-content/uploads/2022/12/Kitron-260x173.jpeg","hotels-thumb-width":260,"hotels-thumb-height":173}},{"ID":2197,"id":2197,"title":"Kitron-8","filename":"Kitron-8.jpeg","filesize":250511,"url":"https://greece-hotel.info/admins/aquavistahotels/wp-content/uploads/2022/12/Kitron-8.jpeg","link":"https://greece-hotel.info/admins/aquavistahotels/hotelss/apricot-sea-luxury-villas-naxos/kitron-8/","alt":"","author":"1","description":"","caption":"","name":"kitron-8","status":"inherit","uploaded_to":2183,"date":"2022-12-08 08:24:46","modified":"2022-12-08 09:44:22","menu_order":0,"mime_type":"image/jpeg","type":"image","subtype":"jpeg","icon":"https://greece-hotel.info/admins/aquavistahotels/wp-includes/images/media/default.png","width":1920,"height":1280,"sizes":{"thumbnail":"https://greece-hotel.info/admins/aquavistahotels/wp-content/uploads/2022/12/Kitron-8-150x150.jpeg","thumbnail-width":150,"thumbnail-height":150,"medium":"https://greece-hotel.info/admins/aquavistahotels/wp-content/uploads/2022/12/Kitron-8-300x200.jpeg","medium-width":300,"medium-height":200,"medium_large":"https://greece-hotel.info/admins/aquavistahotels/wp-content/uploads/2022/12/Kitron-8-768x512.jpeg","medium_large-width":768,"medium_large-height":512,"large":"https://greece-hotel.info/admins/aquavistahotels/wp-content/uploads/2022/12/Kitron-8-1024x683.jpeg","large-width":1024,"large-height":683,"1536x1536":"https://greece-hotel.info/admins/aquavistahotels/wp-content/uploads/2022/12/Kitron-8-1536x1024.jpeg","1536x1536-width":1536,"1536x1536-height":1024,"2048x2048":"https://greece-hotel.info/admins/aquavistahotels/wp-content/uploads/2022/12/Kitron-8.jpeg","2048x2048-width":1920,"2048x2048-height":1280,"hotels-thumb":"https://greece-hotel.info/admins/aquavistahotels/wp-content/uploads/2022/12/Kitron-8-260x173.jpeg","hotels-thumb-width":260,"hotels-thumb-height":173}}],"intro_text":"Maisonette Villa Kitron","book_now":"https://apricotandsea.reserve-online.net/","image":{"src":"https://code.rateparity.com/aquavistahotels.com/2022/12/Kitron-9.jpeg","alt":"alt image"},"excerpt":"One of the Top 2 most spacious residences of Apricot & Sea, maisonette Kitron like the most traditional and well-known drink of Naxos from which it takes its name, gives you the chance...","amenities":"<ul class=\"three-col\">\n<li style=\"font-weight: 400;\" aria-level=\"1\"><span style=\"font-weight: 400;\">Cleaning every day</span></li>\n<li style=\"font-weight: 400;\" aria-level=\"1\"><span style=\"font-weight: 400;\">Bed sheets change every 2 days</span></li>\n<li style=\"font-weight: 400;\" aria-level=\"1\"><span style=\"font-weight: 400;\">Free wifi</span></li>\n<li style=\"font-weight: 400;\" aria-level=\"1\"><span style=\"font-weight: 400;\">Flat-screen satellite tv</span></li>\n<li style=\"font-weight: 400;\" aria-level=\"1\"><span style=\"font-weight: 400;\">Air conditioning</span></li>\n<li style=\"font-weight: 400;\" aria-level=\"1\"><span style=\"font-weight: 400;\">Full kitchen cooking equipment</span></li>\n<li style=\"font-weight: 400;\" aria-level=\"1\"><span style=\"font-weight: 400;\">Dish washer</span></li>\n<li style=\"font-weight: 400;\" aria-level=\"1\"><span style=\"font-weight: 400;\">Oven</span></li>\n<li style=\"font-weight: 400;\" aria-level=\"1\"><span style=\"font-weight: 400;\">Microwave</span></li>\n<li style=\"font-weight: 400;\" aria-level=\"1\"><span style=\"font-weight: 400;\">Coffee machine</span></li>\n<li style=\"font-weight: 400;\" aria-level=\"1\"><span style=\"font-weight: 400;\">Fridge</span></li>\n<li style=\"font-weight: 400;\" aria-level=\"1\"><span style=\"font-weight: 400;\">Washing machine</span></li>\n<li style=\"font-weight: 400;\" aria-level=\"1\"><span style=\"font-weight: 400;\">Iron with iron board</span></li>\n<li style=\"font-weight: 400;\" aria-level=\"1\"><span style=\"font-weight: 400;\">Bathroom and pool towels</span></li>\n<li style=\"font-weight: 400;\" aria-level=\"1\"><span style=\"font-weight: 400;\">Dryer</span></li>\n<li style=\"font-weight: 400;\" aria-level=\"1\"><span style=\"font-weight: 400;\">Fireplace</span></li>\n<li style=\"font-weight: 400;\" aria-level=\"1\"><span style=\"font-weight: 400;\">Safe box</span></li>\n<li style=\"font-weight: 400;\" aria-level=\"1\"><span style=\"font-weight: 400;\">Swimming pool</span></li>\n<li style=\"font-weight: 400;\" aria-level=\"1\"><span style=\"font-weight: 400;\">Barbecue</span></li>\n<li style=\"font-weight: 400;\" aria-level=\"1\"><span style=\"font-weight: 400;\">Outside seating space with pool and sea view</span></li>\n<li style=\"font-weight: 400;\" aria-level=\"1\"><span style=\"font-weight: 400;\">Parking</span></li>\n<li style=\"font-weight: 400;\" aria-level=\"1\"><span style=\"font-weight: 400;\">Storage space</span></li>\n</ul>\n","amenities_with_icons":[{"icon":"https://code.rateparity.com/aquavistahotels.com/2022/09/icon-3-1.svg","name":"ADSL Internet Connection"},{"icon":"https://code.rateparity.com/aquavistahotels.com/2022/07/007-fan.svg","name":"Air Conditioning"},{"icon":"https://code.rateparity.com/aquavistahotels.com/2022/07/handshake.svg","name":"Business Lounge"},{"icon":"https://code.rateparity.com/aquavistahotels.com/2022/07/bar.svg","name":"Bar"}],"gallery":["https://greece-hotel.info/admins/aquavistahotels/wp-content/uploads/2022/12/Kitron.jpeg","https://greece-hotel.info/admins/aquavistahotels/wp-content/uploads/2022/12/Kitron-4.jpeg","https://greece-hotel.info/admins/aquavistahotels/wp-content/uploads/2022/12/Kitron-2.jpeg","https://greece-hotel.info/admins/aquavistahotels/wp-content/uploads/2022/12/Kitron-5.jpeg","https://greece-hotel.info/admins/aquavistahotels/wp-content/uploads/2022/12/Kitron-7-scaled.jpeg","https://greece-hotel.info/admins/aquavistahotels/wp-content/uploads/2022/12/Kitron-8.jpeg","https://greece-hotel.info/admins/aquavistahotels/wp-content/uploads/2022/12/Kitron-3.jpeg","https://greece-hotel.info/admins/aquavistahotels/wp-content/uploads/2022/12/Kitron-9.jpeg"],"seo_title":"Maisonette Villa Kitron | Apricot & Sea Luxury Villas Naxos","seo_description":"Maisonetter Villa Kitron is a spacious 110 sq.m interior for up to 10 guests. Fully-equipped kitchen, Free Wi-Fi. Access to pool & barbecue. Book today!","keywords":"","small_info":"Up to 10 Guests/ pool and sea view","link":{"pathname":"/hotels-in-naxos/apricot-sea-luxury-villas-naxos/rooms/maisonette-villa-kitron","api":"/pages/room/room1","text":"Explore"}},{"description":"Naxos Eye is an independent maisonette for 2-4 of our visitors looking to indulge in the hospitality of Apricot & Sea with access to swimming pool, barbecue and outside seating areas.","title":"Naxos Eye","slider_gallery":[{"ID":2207,"id":2207,"title":"Naxos-Eye-9","filename":"Naxos-Eye-9.jpeg","filesize":231954,"url":"https://greece-hotel.info/admins/aquavistahotels/wp-content/uploads/2022/12/Naxos-Eye-9.jpeg","link":"https://greece-hotel.info/admins/aquavistahotels/hotelss/apricot-sea-luxury-villas-naxos/naxos-eye-9/","alt":"","author":"1","description":"","caption":"","name":"naxos-eye-9","status":"inherit","uploaded_to":2183,"date":"2022-12-08 08:25:27","modified":"2022-12-08 08:25:27","menu_order":0,"mime_type":"image/jpeg","type":"image","subtype":"jpeg","icon":"https://greece-hotel.info/admins/aquavistahotels/wp-includes/images/media/default.png","width":1920,"height":1280,"sizes":{"thumbnail":"https://greece-hotel.info/admins/aquavistahotels/wp-content/uploads/2022/12/Naxos-Eye-9-150x150.jpeg","thumbnail-width":150,"thumbnail-height":150,"medium":"https://greece-hotel.info/admins/aquavistahotels/wp-content/uploads/2022/12/Naxos-Eye-9-300x200.jpeg","medium-width":300,"medium-height":200,"medium_large":"https://greece-hotel.info/admins/aquavistahotels/wp-content/uploads/2022/12/Naxos-Eye-9-768x512.jpeg","medium_large-width":768,"medium_large-height":512,"large":"https://greece-hotel.info/admins/aquavistahotels/wp-content/uploads/2022/12/Naxos-Eye-9-1024x683.jpeg","large-width":1024,"large-height":683,"1536x1536":"https://greece-hotel.info/admins/aquavistahotels/wp-content/uploads/2022/12/Naxos-Eye-9-1536x1024.jpeg","1536x1536-width":1536,"1536x1536-height":1024,"2048x2048":"https://greece-hotel.info/admins/aquavistahotels/wp-content/uploads/2022/12/Naxos-Eye-9.jpeg","2048x2048-width":1920,"2048x2048-height":1280,"hotels-thumb":"https://greece-hotel.info/admins/aquavistahotels/wp-content/uploads/2022/12/Naxos-Eye-9-260x173.jpeg","hotels-thumb-width":260,"hotels-thumb-height":173}},{"ID":2213,"id":2213,"title":"Naxos-Eye-2","filename":"Naxos-Eye-2.jpeg","filesize":217069,"url":"https://greece-hotel.info/admins/aquavistahotels/wp-content/uploads/2022/12/Naxos-Eye-2.jpeg","link":"https://greece-hotel.info/admins/aquavistahotels/hotelss/apricot-sea-luxury-villas-naxos/naxos-eye-2/","alt":"","author":"1","description":"","caption":"","name":"naxos-eye-2","status":"inherit","uploaded_to":2183,"date":"2022-12-08 08:25:39","modified":"2022-12-08 08:25:39","menu_order":0,"mime_type":"image/jpeg","type":"image","subtype":"jpeg","icon":"https://greece-hotel.info/admins/aquavistahotels/wp-includes/images/media/default.png","width":1920,"height":1280,"sizes":{"thumbnail":"https://greece-hotel.info/admins/aquavistahotels/wp-content/uploads/2022/12/Naxos-Eye-2-150x150.jpeg","thumbnail-width":150,"thumbnail-height":150,"medium":"https://greece-hotel.info/admins/aquavistahotels/wp-content/uploads/2022/12/Naxos-Eye-2-300x200.jpeg","medium-width":300,"medium-height":200,"medium_large":"https://greece-hotel.info/admins/aquavistahotels/wp-content/uploads/2022/12/Naxos-Eye-2-768x512.jpeg","medium_large-width":768,"medium_large-height":512,"large":"https://greece-hotel.info/admins/aquavistahotels/wp-content/uploads/2022/12/Naxos-Eye-2-1024x683.jpeg","large-width":1024,"large-height":683,"1536x1536":"https://greece-hotel.info/admins/aquavistahotels/wp-content/uploads/2022/12/Naxos-Eye-2-1536x1024.jpeg","1536x1536-width":1536,"1536x1536-height":1024,"2048x2048":"https://greece-hotel.info/admins/aquavistahotels/wp-content/uploads/2022/12/Naxos-Eye-2.jpeg","2048x2048-width":1920,"2048x2048-height":1280,"hotels-thumb":"https://greece-hotel.info/admins/aquavistahotels/wp-content/uploads/2022/12/Naxos-Eye-2-260x173.jpeg","hotels-thumb-width":260,"hotels-thumb-height":173}},{"ID":2206,"id":2206,"title":"Naxos-Eye-8","filename":"Naxos-Eye-8.jpeg","filesize":184166,"url":"https://greece-hotel.info/admins/aquavistahotels/wp-content/uploads/2022/12/Naxos-Eye-8.jpeg","link":"https://greece-hotel.info/admins/aquavistahotels/hotelss/apricot-sea-luxury-villas-naxos/naxos-eye-8/","alt":"","author":"1","description":"","caption":"","name":"naxos-eye-8","status":"inherit","uploaded_to":2183,"date":"2022-12-08 08:25:25","modified":"2022-12-08 08:25:25","menu_order":0,"mime_type":"image/jpeg","type":"image","subtype":"jpeg","icon":"https://greece-hotel.info/admins/aquavistahotels/wp-includes/images/media/default.png","width":1920,"height":1280,"sizes":{"thumbnail":"https://greece-hotel.info/admins/aquavistahotels/wp-content/uploads/2022/12/Naxos-Eye-8-150x150.jpeg","thumbnail-width":150,"thumbnail-height":150,"medium":"https://greece-hotel.info/admins/aquavistahotels/wp-content/uploads/2022/12/Naxos-Eye-8-300x200.jpeg","medium-width":300,"medium-height":200,"medium_large":"https://greece-hotel.info/admins/aquavistahotels/wp-content/uploads/2022/12/Naxos-Eye-8-768x512.jpeg","medium_large-width":768,"medium_large-height":512,"large":"https://greece-hotel.info/admins/aquavistahotels/wp-content/uploads/2022/12/Naxos-Eye-8-1024x683.jpeg","large-width":1024,"large-height":683,"1536x1536":"https://greece-hotel.info/admins/aquavistahotels/wp-content/uploads/2022/12/Naxos-Eye-8-1536x1024.jpeg","1536x1536-width":1536,"1536x1536-height":1024,"2048x2048":"https://greece-hotel.info/admins/aquavistahotels/wp-content/uploads/2022/12/Naxos-Eye-8.jpeg","2048x2048-width":1920,"2048x2048-height":1280,"hotels-thumb":"https://greece-hotel.info/admins/aquavistahotels/wp-content/uploads/2022/12/Naxos-Eye-8-260x173.jpeg","hotels-thumb-width":260,"hotels-thumb-height":173}},{"ID":2204,"id":2204,"title":"Naxos-Eye-6","filename":"Naxos-Eye-6.jpeg","filesize":250511,"url":"https://greece-hotel.info/admins/aquavistahotels/wp-content/uploads/2022/12/Naxos-Eye-6.jpeg","link":"https://greece-hotel.info/admins/aquavistahotels/hotelss/apricot-sea-luxury-villas-naxos/naxos-eye-6/","alt":"","author":"1","description":"","caption":"","name":"naxos-eye-6","status":"inherit","uploaded_to":2183,"date":"2022-12-08 08:25:23","modified":"2022-12-08 10:11:45","menu_order":0,"mime_type":"image/jpeg","type":"image","subtype":"jpeg","icon":"https://greece-hotel.info/admins/aquavistahotels/wp-includes/images/media/default.png","width":1920,"height":1280,"sizes":{"thumbnail":"https://greece-hotel.info/admins/aquavistahotels/wp-content/uploads/2022/12/Naxos-Eye-6-150x150.jpeg","thumbnail-width":150,"thumbnail-height":150,"medium":"https://greece-hotel.info/admins/aquavistahotels/wp-content/uploads/2022/12/Naxos-Eye-6-300x200.jpeg","medium-width":300,"medium-height":200,"medium_large":"https://greece-hotel.info/admins/aquavistahotels/wp-content/uploads/2022/12/Naxos-Eye-6-768x512.jpeg","medium_large-width":768,"medium_large-height":512,"large":"https://greece-hotel.info/admins/aquavistahotels/wp-content/uploads/2022/12/Naxos-Eye-6-1024x683.jpeg","large-width":1024,"large-height":683,"1536x1536":"https://greece-hotel.info/admins/aquavistahotels/wp-content/uploads/2022/12/Naxos-Eye-6-1536x1024.jpeg","1536x1536-width":1536,"1536x1536-height":1024,"2048x2048":"https://greece-hotel.info/admins/aquavistahotels/wp-content/uploads/2022/12/Naxos-Eye-6.jpeg","2048x2048-width":1920,"2048x2048-height":1280,"hotels-thumb":"https://greece-hotel.info/admins/aquavistahotels/wp-content/uploads/2022/12/Naxos-Eye-6-260x173.jpeg","hotels-thumb-width":260,"hotels-thumb-height":173}}],"intro_text":"Naxos Eye","book_now":"https://apricotandsea.reserve-online.net/","image":{"src":"https://code.rateparity.com/aquavistahotels.com/2022/12/Naxos-Eye-14.jpeg","alt":"alt image"},"excerpt":"Naxos Eye is an independent maisonette for 2-4 of our visitors looking to indulge in the hospitality of Apricot & Sea with access to swimming pool, barbecue and outside seating areas.","amenities":"<ul class=\"three-col\">\n<li style=\"font-weight: 400;\" aria-level=\"1\"><span style=\"font-weight: 400;\">Cleaning every day</span></li>\n<li style=\"font-weight: 400;\" aria-level=\"1\"><span style=\"font-weight: 400;\">Bed sheets change every 2 days</span></li>\n<li style=\"font-weight: 400;\" aria-level=\"1\"><span style=\"font-weight: 400;\">Free wifi</span></li>\n<li style=\"font-weight: 400;\" aria-level=\"1\"><span style=\"font-weight: 400;\">Flat-screen satellite tv</span></li>\n<li style=\"font-weight: 400;\" aria-level=\"1\"><span style=\"font-weight: 400;\">Air conditioning</span></li>\n<li style=\"font-weight: 400;\" aria-level=\"1\"><span style=\"font-weight: 400;\">Full kitchen cooking equipment</span></li>\n<li style=\"font-weight: 400;\" aria-level=\"1\"><span style=\"font-weight: 400;\">Dish washer</span></li>\n<li style=\"font-weight: 400;\" aria-level=\"1\"><span style=\"font-weight: 400;\">Oven</span></li>\n<li style=\"font-weight: 400;\" aria-level=\"1\"><span style=\"font-weight: 400;\">Microwave</span></li>\n<li style=\"font-weight: 400;\" aria-level=\"1\"><span style=\"font-weight: 400;\">Coffee machine</span></li>\n<li style=\"font-weight: 400;\" aria-level=\"1\"><span style=\"font-weight: 400;\">Fridge</span></li>\n<li style=\"font-weight: 400;\" aria-level=\"1\"><span style=\"font-weight: 400;\">Washing machine</span></li>\n<li style=\"font-weight: 400;\" aria-level=\"1\"><span style=\"font-weight: 400;\">Iron with iron board</span></li>\n<li style=\"font-weight: 400;\" aria-level=\"1\"><span style=\"font-weight: 400;\">Bathroom and pool towels</span></li>\n<li style=\"font-weight: 400;\" aria-level=\"1\"><span style=\"font-weight: 400;\">Dryer</span></li>\n<li style=\"font-weight: 400;\" aria-level=\"1\"><span style=\"font-weight: 400;\">Safe Box</span></li>\n<li style=\"font-weight: 400;\" aria-level=\"1\"><span style=\"font-weight: 400;\">Swimming pool</span></li>\n<li style=\"font-weight: 400;\" aria-level=\"1\"><span style=\"font-weight: 400;\">Barbecue</span></li>\n<li style=\"font-weight: 400;\" aria-level=\"1\"><span style=\"font-weight: 400;\">Outside seating space with pool and sea view</span></li>\n<li style=\"font-weight: 400;\" aria-level=\"1\"><span style=\"font-weight: 400;\">Parking</span></li>\n</ul>\n","amenities_with_icons":[{"icon":"https://code.rateparity.com/aquavistahotels.com/2022/09/icon-3-1.svg","name":"ADSL Internet Connection"},{"icon":"https://code.rateparity.com/aquavistahotels.com/2022/07/007-fan.svg","name":"Air Conditioning"},{"icon":"https://code.rateparity.com/aquavistahotels.com/2022/07/handshake.svg","name":"Business Lounge"},{"icon":"https://code.rateparity.com/aquavistahotels.com/2022/07/bar.svg","name":"Bar"}],"gallery":["https://greece-hotel.info/admins/aquavistahotels/wp-content/uploads/2022/12/Naxos-Eye-9.jpeg","https://greece-hotel.info/admins/aquavistahotels/wp-content/uploads/2022/12/Naxos-Eye-8.jpeg","https://greece-hotel.info/admins/aquavistahotels/wp-content/uploads/2022/12/Naxos-Eye-5.jpeg","https://greece-hotel.info/admins/aquavistahotels/wp-content/uploads/2022/12/Naxos-Eye-2.jpeg","https://greece-hotel.info/admins/aquavistahotels/wp-content/uploads/2022/12/Naxos-Eye.jpeg","https://greece-hotel.info/admins/aquavistahotels/wp-content/uploads/2022/12/Naxos-Eye-3.jpeg","https://greece-hotel.info/admins/aquavistahotels/wp-content/uploads/2022/12/Naxos-Eye-7.jpeg","https://greece-hotel.info/admins/aquavistahotels/wp-content/uploads/2022/12/Naxos-Eye-6.jpeg","https://greece-hotel.info/admins/aquavistahotels/wp-content/uploads/2022/12/Naxos-Eye-12.jpeg","https://greece-hotel.info/admins/aquavistahotels/wp-content/uploads/2022/12/Naxos-Eye-10-scaled.jpeg","https://greece-hotel.info/admins/aquavistahotels/wp-content/uploads/2022/12/Naxos-Eye-11-scaled.jpeg","https://greece-hotel.info/admins/aquavistahotels/wp-content/uploads/2022/12/Naxos-Eye-14.jpeg"],"seo_title":"Naxos Eye | Rooms | Apricot & Sea Luxury Villas Naxos","seo_description":"Naxos Eye is a charming maisonnette with a spacious 53 sq.m interior. Fully-equipped kitchen. Free Wi-Fi. Access to pool & barbecue. Sea views. Book today!","keywords":"","small_info":"Up to 2-4 Guests/ pool and sea view","link":{"pathname":"/hotels-in-naxos/apricot-sea-luxury-villas-naxos/rooms/naxos-eye","api":"/pages/room/room1","text":"Explore"}},{"description":"Orkos studio, which took its name from the beautiful small beach that cools our visitors in the summer, is ideal for those who are looking for a beautiful small space...","title":"Orkos Studio","slider_gallery":[{"ID":2216,"id":2216,"title":"Orkos-5","filename":"Orkos-5.jpeg","filesize":171802,"url":"https://greece-hotel.info/admins/aquavistahotels/wp-content/uploads/2022/12/Orkos-5.jpeg","link":"https://greece-hotel.info/admins/aquavistahotels/hotelss/apricot-sea-luxury-villas-naxos/orkos-5/","alt":"","author":"1","description":"","caption":"","name":"orkos-5","status":"inherit","uploaded_to":2183,"date":"2022-12-08 08:26:00","modified":"2022-12-08 08:26:00","menu_order":0,"mime_type":"image/jpeg","type":"image","subtype":"jpeg","icon":"https://greece-hotel.info/admins/aquavistahotels/wp-includes/images/media/default.png","width":1920,"height":1280,"sizes":{"thumbnail":"https://greece-hotel.info/admins/aquavistahotels/wp-content/uploads/2022/12/Orkos-5-150x150.jpeg","thumbnail-width":150,"thumbnail-height":150,"medium":"https://greece-hotel.info/admins/aquavistahotels/wp-content/uploads/2022/12/Orkos-5-300x200.jpeg","medium-width":300,"medium-height":200,"medium_large":"https://greece-hotel.info/admins/aquavistahotels/wp-content/uploads/2022/12/Orkos-5-768x512.jpeg","medium_large-width":768,"medium_large-height":512,"large":"https://greece-hotel.info/admins/aquavistahotels/wp-content/uploads/2022/12/Orkos-5-1024x683.jpeg","large-width":1024,"large-height":683,"1536x1536":"https://greece-hotel.info/admins/aquavistahotels/wp-content/uploads/2022/12/Orkos-5-1536x1024.jpeg","1536x1536-width":1536,"1536x1536-height":1024,"2048x2048":"https://greece-hotel.info/admins/aquavistahotels/wp-content/uploads/2022/12/Orkos-5.jpeg","2048x2048-width":1920,"2048x2048-height":1280,"hotels-thumb":"https://greece-hotel.info/admins/aquavistahotels/wp-content/uploads/2022/12/Orkos-5-260x173.jpeg","hotels-thumb-width":260,"hotels-thumb-height":173}},{"ID":2215,"id":2215,"title":"Orkos-4","filename":"Orkos-4.jpeg","filesize":333956,"url":"https://greece-hotel.info/admins/aquavistahotels/wp-content/uploads/2022/12/Orkos-4.jpeg","link":"https://greece-hotel.info/admins/aquavistahotels/hotelss/apricot-sea-luxury-villas-naxos/orkos-4/","alt":"","author":"1","description":"","caption":"","name":"orkos-4","status":"inherit","uploaded_to":2183,"date":"2022-12-08 08:25:59","modified":"2022-12-08 09:29:09","menu_order":0,"mime_type":"image/jpeg","type":"image","subtype":"jpeg","icon":"https://greece-hotel.info/admins/aquavistahotels/wp-includes/images/media/default.png","width":1920,"height":1280,"sizes":{"thumbnail":"https://greece-hotel.info/admins/aquavistahotels/wp-content/uploads/2022/12/Orkos-4-150x150.jpeg","thumbnail-width":150,"thumbnail-height":150,"medium":"https://greece-hotel.info/admins/aquavistahotels/wp-content/uploads/2022/12/Orkos-4-300x200.jpeg","medium-width":300,"medium-height":200,"medium_large":"https://greece-hotel.info/admins/aquavistahotels/wp-content/uploads/2022/12/Orkos-4-768x512.jpeg","medium_large-width":768,"medium_large-height":512,"large":"https://greece-hotel.info/admins/aquavistahotels/wp-content/uploads/2022/12/Orkos-4-1024x683.jpeg","large-width":1024,"large-height":683,"1536x1536":"https://greece-hotel.info/admins/aquavistahotels/wp-content/uploads/2022/12/Orkos-4-1536x1024.jpeg","1536x1536-width":1536,"1536x1536-height":1024,"2048x2048":"https://greece-hotel.info/admins/aquavistahotels/wp-content/uploads/2022/12/Orkos-4.jpeg","2048x2048-width":1920,"2048x2048-height":1280,"hotels-thumb":"https://greece-hotel.info/admins/aquavistahotels/wp-content/uploads/2022/12/Orkos-4-260x173.jpeg","hotels-thumb-width":260,"hotels-thumb-height":173}}],"intro_text":"Orkos Studio","book_now":"https://apricotandsea.reserve-online.net/","image":{"src":"https://code.rateparity.com/aquavistahotels.com/2022/12/Orkos-5.jpeg","alt":"alt image"},"excerpt":"Orkos studio, which took its name from the beautiful small beach that cools our visitors in the summer, is ideal for those who are looking for a beautiful small space...","amenities":"<ul class=\"three-col\">\n<li style=\"font-weight: 400;\" aria-level=\"1\"><span style=\"font-weight: 400;\">Cleaning every day</span></li>\n<li style=\"font-weight: 400;\" aria-level=\"1\"><span style=\"font-weight: 400;\">Bed sheets change every 2 days</span></li>\n<li style=\"font-weight: 400;\" aria-level=\"1\"><span style=\"font-weight: 400;\">Free wifi</span></li>\n<li style=\"font-weight: 400;\" aria-level=\"1\"><span style=\"font-weight: 400;\">Flat-screen satellite tv</span></li>\n<li style=\"font-weight: 400;\" aria-level=\"1\"><span style=\"font-weight: 400;\">Air conditioning</span></li>\n<li style=\"font-weight: 400;\" aria-level=\"1\"><span style=\"font-weight: 400;\">Full kitchen cooking equipment</span></li>\n<li style=\"font-weight: 400;\" aria-level=\"1\"><span style=\"font-weight: 400;\">Oven</span></li>\n<li style=\"font-weight: 400;\" aria-level=\"1\"><span style=\"font-weight: 400;\">Microwave</span></li>\n<li style=\"font-weight: 400;\" aria-level=\"1\"><span style=\"font-weight: 400;\">Coffee machine</span></li>\n<li style=\"font-weight: 400;\" aria-level=\"1\"><span style=\"font-weight: 400;\">Fridge</span></li>\n<li style=\"font-weight: 400;\" aria-level=\"1\"><span style=\"font-weight: 400;\">Washing machine</span></li>\n<li style=\"font-weight: 400;\" aria-level=\"1\"><span style=\"font-weight: 400;\">Iron with iron board</span></li>\n<li style=\"font-weight: 400;\" aria-level=\"1\"><span style=\"font-weight: 400;\">Bathroom and pool towels</span></li>\n<li style=\"font-weight: 400;\" aria-level=\"1\"><span style=\"font-weight: 400;\">Dryer</span></li>\n<li style=\"font-weight: 400;\" aria-level=\"1\"><span style=\"font-weight: 400;\">Safe Box</span></li>\n<li style=\"font-weight: 400;\" aria-level=\"1\"><span style=\"font-weight: 400;\">Swimming pool</span></li>\n<li style=\"font-weight: 400;\" aria-level=\"1\"><span style=\"font-weight: 400;\">Barbecue</span></li>\n<li style=\"font-weight: 400;\" aria-level=\"1\"><span style=\"font-weight: 400;\">Outside seating space with pool and sea view</span></li>\n<li style=\"font-weight: 400;\" aria-level=\"1\"><span style=\"font-weight: 400;\">Parking</span></li>\n</ul>\n","amenities_with_icons":[{"icon":"https://code.rateparity.com/aquavistahotels.com/2022/09/icon-3-1.svg","name":"ADSL Internet Connection"},{"icon":"https://code.rateparity.com/aquavistahotels.com/2022/07/007-fan.svg","name":"Air Conditioning"},{"icon":"https://code.rateparity.com/aquavistahotels.com/2022/07/handshake.svg","name":"Business Lounge"},{"icon":"https://code.rateparity.com/aquavistahotels.com/2022/07/bar.svg","name":"Bar"}],"gallery":["https://greece-hotel.info/admins/aquavistahotels/wp-content/uploads/2022/12/Orkos-5.jpeg","https://greece-hotel.info/admins/aquavistahotels/wp-content/uploads/2022/12/Orkos-4.jpeg","https://greece-hotel.info/admins/aquavistahotels/wp-content/uploads/2022/12/Orkos-3.jpeg","https://greece-hotel.info/admins/aquavistahotels/wp-content/uploads/2022/12/Orkos-2.jpeg","https://greece-hotel.info/admins/aquavistahotels/wp-content/uploads/2022/12/Orkos-6.jpeg","https://greece-hotel.info/admins/aquavistahotels/wp-content/uploads/2022/12/Orkos.jpeg"],"seo_title":"Orkos Studio | Rooms | Apricot & Sea Luxury Villas Naxos","seo_description":"Orkos Studio is a beautiful 30 sq.m space for up to 4 guests. Direct access to the pool & barbecue. Outdoor seating. Stunning sea views. Book today!","keywords":"","small_info":"Up to 4 Guests/ Aegean view","link":{"pathname":"/hotels-in-naxos/apricot-sea-luxury-villas-naxos/rooms/orkos-studio","api":"/pages/room/room1","text":"Explore"}},{"description":"One of the 2 gorgeous studios of Apricot & Sea, Waves is the perfect option for visitors looking for a space that can accommodate up to 2 people and can also grant you access...","title":"Waves Studio","slider_gallery":[{"ID":2243,"id":2243,"title":"Portara","filename":"Portara-1.jpeg","filesize":235050,"url":"https://greece-hotel.info/admins/aquavistahotels/wp-content/uploads/2022/12/Portara-1.jpeg","link":"https://greece-hotel.info/admins/aquavistahotels/hotelss/apricot-sea-luxury-villas-naxos/portara-11/","alt":"","author":"1","description":"","caption":"","name":"portara-11","status":"inherit","uploaded_to":2183,"date":"2022-12-08 08:27:15","modified":"2022-12-08 08:27:15","menu_order":0,"mime_type":"image/jpeg","type":"image","subtype":"jpeg","icon":"https://greece-hotel.info/admins/aquavistahotels/wp-includes/images/media/default.png","width":1920,"height":1280,"sizes":{"thumbnail":"https://greece-hotel.info/admins/aquavistahotels/wp-content/uploads/2022/12/Portara-1-150x150.jpeg","thumbnail-width":150,"thumbnail-height":150,"medium":"https://greece-hotel.info/admins/aquavistahotels/wp-content/uploads/2022/12/Portara-1-300x200.jpeg","medium-width":300,"medium-height":200,"medium_large":"https://greece-hotel.info/admins/aquavistahotels/wp-content/uploads/2022/12/Portara-1-768x512.jpeg","medium_large-width":768,"medium_large-height":512,"large":"https://greece-hotel.info/admins/aquavistahotels/wp-content/uploads/2022/12/Portara-1-1024x683.jpeg","large-width":1024,"large-height":683,"1536x1536":"https://greece-hotel.info/admins/aquavistahotels/wp-content/uploads/2022/12/Portara-1-1536x1024.jpeg","1536x1536-width":1536,"1536x1536-height":1024,"2048x2048":"https://greece-hotel.info/admins/aquavistahotels/wp-content/uploads/2022/12/Portara-1.jpeg","2048x2048-width":1920,"2048x2048-height":1280,"hotels-thumb":"https://greece-hotel.info/admins/aquavistahotels/wp-content/uploads/2022/12/Portara-1-260x173.jpeg","hotels-thumb-width":260,"hotels-thumb-height":173}},{"ID":2242,"id":2242,"title":"Apricot-Villas-179","filename":"Apricot-Villas-179.jpeg","filesize":288850,"url":"https://greece-hotel.info/admins/aquavistahotels/wp-content/uploads/2022/12/Apricot-Villas-179.jpeg","link":"https://greece-hotel.info/admins/aquavistahotels/hotelss/apricot-sea-luxury-villas-naxos/apricot-villas-179/","alt":"","author":"1","description":"","caption":"","name":"apricot-villas-179","status":"inherit","uploaded_to":2183,"date":"2022-12-08 08:27:14","modified":"2022-12-08 08:27:14","menu_order":0,"mime_type":"image/jpeg","type":"image","subtype":"jpeg","icon":"https://greece-hotel.info/admins/aquavistahotels/wp-includes/images/media/default.png","width":1920,"height":1280,"sizes":{"thumbnail":"https://greece-hotel.info/admins/aquavistahotels/wp-content/uploads/2022/12/Apricot-Villas-179-150x150.jpeg","thumbnail-width":150,"thumbnail-height":150,"medium":"https://greece-hotel.info/admins/aquavistahotels/wp-content/uploads/2022/12/Apricot-Villas-179-300x200.jpeg","medium-width":300,"medium-height":200,"medium_large":"https://greece-hotel.info/admins/aquavistahotels/wp-content/uploads/2022/12/Apricot-Villas-179-768x512.jpeg","medium_large-width":768,"medium_large-height":512,"large":"https://greece-hotel.info/admins/aquavistahotels/wp-content/uploads/2022/12/Apricot-Villas-179-1024x683.jpeg","large-width":1024,"large-height":683,"1536x1536":"https://greece-hotel.info/admins/aquavistahotels/wp-content/uploads/2022/12/Apricot-Villas-179-1536x1024.jpeg","1536x1536-width":1536,"1536x1536-height":1024,"2048x2048":"https://greece-hotel.info/admins/aquavistahotels/wp-content/uploads/2022/12/Apricot-Villas-179.jpeg","2048x2048-width":1920,"2048x2048-height":1280,"hotels-thumb":"https://greece-hotel.info/admins/aquavistahotels/wp-content/uploads/2022/12/Apricot-Villas-179-260x173.jpeg","hotels-thumb-width":260,"hotels-thumb-height":173}}],"intro_text":"Waves Studio","book_now":"https://apricotandsea.reserve-online.net/","image":{"src":"https://code.rateparity.com/aquavistahotels.com/2022/12/Portara-1.jpeg","alt":"alt image"},"excerpt":"One of the 2 gorgeous studios of Apricot & Sea, Waves is the perfect option for visitors looking for a space that can accommodate up to 2 people and can also grant you access...","amenities":"<ul class=\"three-col\">\n<li style=\"font-weight: 400;\" aria-level=\"1\"><span style=\"font-weight: 400;\">Cleaning every day</span></li>\n<li style=\"font-weight: 400;\" aria-level=\"1\"><span style=\"font-weight: 400;\">Bed sheets change every 2 days</span></li>\n<li style=\"font-weight: 400;\" aria-level=\"1\"><span style=\"font-weight: 400;\">Free wifi</span></li>\n<li style=\"font-weight: 400;\" aria-level=\"1\"><span style=\"font-weight: 400;\">Flat-screen satellite tv</span></li>\n<li style=\"font-weight: 400;\" aria-level=\"1\"><span style=\"font-weight: 400;\">Air conditioning</span></li>\n<li style=\"font-weight: 400;\" aria-level=\"1\"><span style=\"font-weight: 400;\">Full kitchen cooking equipment</span></li>\n<li style=\"font-weight: 400;\" aria-level=\"1\"><span style=\"font-weight: 400;\">Oven</span></li>\n<li style=\"font-weight: 400;\" aria-level=\"1\"><span style=\"font-weight: 400;\">Microwave</span></li>\n<li style=\"font-weight: 400;\" aria-level=\"1\"><span style=\"font-weight: 400;\">Coffee machine</span></li>\n<li style=\"font-weight: 400;\" aria-level=\"1\"><span style=\"font-weight: 400;\">Fridge</span></li>\n<li style=\"font-weight: 400;\" aria-level=\"1\"><span style=\"font-weight: 400;\">Washing machine</span></li>\n<li style=\"font-weight: 400;\" aria-level=\"1\"><span style=\"font-weight: 400;\">Iron with iron board</span></li>\n<li style=\"font-weight: 400;\" aria-level=\"1\"><span style=\"font-weight: 400;\">Bathroom and pool towels</span></li>\n<li style=\"font-weight: 400;\" aria-level=\"1\"><span style=\"font-weight: 400;\">Dryer</span></li>\n<li style=\"font-weight: 400;\" aria-level=\"1\"><span style=\"font-weight: 400;\">Safe Box</span></li>\n<li style=\"font-weight: 400;\" aria-level=\"1\"><span style=\"font-weight: 400;\">Swimming pool</span></li>\n<li style=\"font-weight: 400;\" aria-level=\"1\"><span style=\"font-weight: 400;\">Barbecue</span></li>\n<li style=\"font-weight: 400;\" aria-level=\"1\"><span style=\"font-weight: 400;\">Outside seating space with pool and sea view</span></li>\n<li style=\"font-weight: 400;\" aria-level=\"1\"><span style=\"font-weight: 400;\">Parking</span></li>\n<li style=\"font-weight: 400;\" aria-level=\"1\"><span style=\"font-weight: 400;\">Storage space</span></li>\n</ul>\n","amenities_with_icons":[{"icon":"https://code.rateparity.com/aquavistahotels.com/2022/09/icon-3-1.svg","name":"ADSL Internet Connection"},{"icon":"https://code.rateparity.com/aquavistahotels.com/2022/07/007-fan.svg","name":"Air Conditioning"},{"icon":"https://code.rateparity.com/aquavistahotels.com/2022/07/handshake.svg","name":"Business Lounge"},{"icon":"https://code.rateparity.com/aquavistahotels.com/2022/07/bar.svg","name":"Bar"}],"gallery":["https://greece-hotel.info/admins/aquavistahotels/wp-content/uploads/2022/12/Portara-1.jpeg","https://greece-hotel.info/admins/aquavistahotels/wp-content/uploads/2022/12/Apricot-Villas-179.jpeg","https://greece-hotel.info/admins/aquavistahotels/wp-content/uploads/2022/12/apricot_webstavroshabakis-21.jpeg","https://greece-hotel.info/admins/aquavistahotels/wp-content/uploads/2022/12/apricot_webstavroshabakis-62-1.jpeg"],"seo_title":"Waves Studio | Rooms | Apricot & Sea Luxury Villas Naxos","seo_description":"Waves Studio is a gorgeous 22 sq. m interior for 2 guests. Comfortable double bed, direct access to swimming pool & barbecue. Sea views. Book this studio today!","keywords":"","small_info":"Up to 2 Guests/ pool and sea view","link":{"pathname":"/hotels-in-naxos/apricot-sea-luxury-villas-naxos/rooms/waves-studio","api":"/pages/room/room1","text":"Explore"}},{"description":"For our visitors that prefer to enjoy the most unique and picturesque views from a little bit higher altitude than the rest, we arranged to build maisonette Kouros a little bit higher than the rest of the residences and also...","title":"Villa Kouros","slider_gallery":[{"ID":2222,"id":2222,"title":"Kouros-5","filename":"Kouros-5.jpeg","filesize":179896,"url":"https://greece-hotel.info/admins/aquavistahotels/wp-content/uploads/2022/12/Kouros-5.jpeg","link":"https://greece-hotel.info/admins/aquavistahotels/hotelss/apricot-sea-luxury-villas-naxos/kouros-5/","alt":"","author":"1","description":"","caption":"","name":"kouros-5","status":"inherit","uploaded_to":2183,"date":"2022-12-08 08:26:20","modified":"2022-12-08 08:26:20","menu_order":0,"mime_type":"image/jpeg","type":"image","subtype":"jpeg","icon":"https://greece-hotel.info/admins/aquavistahotels/wp-includes/images/media/default.png","width":1920,"height":1280,"sizes":{"thumbnail":"https://greece-hotel.info/admins/aquavistahotels/wp-content/uploads/2022/12/Kouros-5-150x150.jpeg","thumbnail-width":150,"thumbnail-height":150,"medium":"https://greece-hotel.info/admins/aquavistahotels/wp-content/uploads/2022/12/Kouros-5-300x200.jpeg","medium-width":300,"medium-height":200,"medium_large":"https://greece-hotel.info/admins/aquavistahotels/wp-content/uploads/2022/12/Kouros-5-768x512.jpeg","medium_large-width":768,"medium_large-height":512,"large":"https://greece-hotel.info/admins/aquavistahotels/wp-content/uploads/2022/12/Kouros-5-1024x683.jpeg","large-width":1024,"large-height":683,"1536x1536":"https://greece-hotel.info/admins/aquavistahotels/wp-content/uploads/2022/12/Kouros-5-1536x1024.jpeg","1536x1536-width":1536,"1536x1536-height":1024,"2048x2048":"https://greece-hotel.info/admins/aquavistahotels/wp-content/uploads/2022/12/Kouros-5.jpeg","2048x2048-width":1920,"2048x2048-height":1280,"hotels-thumb":"https://greece-hotel.info/admins/aquavistahotels/wp-content/uploads/2022/12/Kouros-5-260x173.jpeg","hotels-thumb-width":260,"hotels-thumb-height":173}},{"ID":2231,"id":2231,"title":"Kouros-2","filename":"Kouros-2.jpeg","filesize":377876,"url":"https://greece-hotel.info/admins/aquavistahotels/wp-content/uploads/2022/12/Kouros-2.jpeg","link":"https://greece-hotel.info/admins/aquavistahotels/hotelss/apricot-sea-luxury-villas-naxos/kouros-2/","alt":"","author":"1","description":"","caption":"","name":"kouros-2","status":"inherit","uploaded_to":2183,"date":"2022-12-08 08:26:32","modified":"2022-12-08 08:26:32","menu_order":0,"mime_type":"image/jpeg","type":"image","subtype":"jpeg","icon":"https://greece-hotel.info/admins/aquavistahotels/wp-includes/images/media/default.png","width":1920,"height":1280,"sizes":{"thumbnail":"https://greece-hotel.info/admins/aquavistahotels/wp-content/uploads/2022/12/Kouros-2-150x150.jpeg","thumbnail-width":150,"thumbnail-height":150,"medium":"https://greece-hotel.info/admins/aquavistahotels/wp-content/uploads/2022/12/Kouros-2-300x200.jpeg","medium-width":300,"medium-height":200,"medium_large":"https://greece-hotel.info/admins/aquavistahotels/wp-content/uploads/2022/12/Kouros-2-768x512.jpeg","medium_large-width":768,"medium_large-height":512,"large":"https://greece-hotel.info/admins/aquavistahotels/wp-content/uploads/2022/12/Kouros-2-1024x683.jpeg","large-width":1024,"large-height":683,"1536x1536":"https://greece-hotel.info/admins/aquavistahotels/wp-content/uploads/2022/12/Kouros-2-1536x1024.jpeg","1536x1536-width":1536,"1536x1536-height":1024,"2048x2048":"https://greece-hotel.info/admins/aquavistahotels/wp-content/uploads/2022/12/Kouros-2.jpeg","2048x2048-width":1920,"2048x2048-height":1280,"hotels-thumb":"https://greece-hotel.info/admins/aquavistahotels/wp-content/uploads/2022/12/Kouros-2-260x173.jpeg","hotels-thumb-width":260,"hotels-thumb-height":173}},{"ID":2224,"id":2224,"title":"Kouros-7","filename":"Kouros-7.jpeg","filesize":174686,"url":"https://greece-hotel.info/admins/aquavistahotels/wp-content/uploads/2022/12/Kouros-7.jpeg","link":"https://greece-hotel.info/admins/aquavistahotels/hotelss/apricot-sea-luxury-villas-naxos/kouros-7/","alt":"","author":"1","description":"","caption":"","name":"kouros-7","status":"inherit","uploaded_to":2183,"date":"2022-12-08 08:26:22","modified":"2022-12-08 09:12:44","menu_order":0,"mime_type":"image/jpeg","type":"image","subtype":"jpeg","icon":"https://greece-hotel.info/admins/aquavistahotels/wp-includes/images/media/default.png","width":1920,"height":1280,"sizes":{"thumbnail":"https://greece-hotel.info/admins/aquavistahotels/wp-content/uploads/2022/12/Kouros-7-150x150.jpeg","thumbnail-width":150,"thumbnail-height":150,"medium":"https://greece-hotel.info/admins/aquavistahotels/wp-content/uploads/2022/12/Kouros-7-300x200.jpeg","medium-width":300,"medium-height":200,"medium_large":"https://greece-hotel.info/admins/aquavistahotels/wp-content/uploads/2022/12/Kouros-7-768x512.jpeg","medium_large-width":768,"medium_large-height":512,"large":"https://greece-hotel.info/admins/aquavistahotels/wp-content/uploads/2022/12/Kouros-7-1024x683.jpeg","large-width":1024,"large-height":683,"1536x1536":"https://greece-hotel.info/admins/aquavistahotels/wp-content/uploads/2022/12/Kouros-7-1536x1024.jpeg","1536x1536-width":1536,"1536x1536-height":1024,"2048x2048":"https://greece-hotel.info/admins/aquavistahotels/wp-content/uploads/2022/12/Kouros-7.jpeg","2048x2048-width":1920,"2048x2048-height":1280,"hotels-thumb":"https://greece-hotel.info/admins/aquavistahotels/wp-content/uploads/2022/12/Kouros-7-260x173.jpeg","hotels-thumb-width":260,"hotels-thumb-height":173}},{"ID":2226,"id":2226,"title":"Kouros-9","filename":"Kouros-9.jpeg","filesize":313514,"url":"https://greece-hotel.info/admins/aquavistahotels/wp-content/uploads/2022/12/Kouros-9.jpeg","link":"https://greece-hotel.info/admins/aquavistahotels/hotelss/apricot-sea-luxury-villas-naxos/kouros-9/","alt":"","author":"1","description":"","caption":"","name":"kouros-9","status":"inherit","uploaded_to":2183,"date":"2022-12-08 08:26:25","modified":"2022-12-08 08:26:25","menu_order":0,"mime_type":"image/jpeg","type":"image","subtype":"jpeg","icon":"https://greece-hotel.info/admins/aquavistahotels/wp-includes/images/media/default.png","width":1920,"height":1280,"sizes":{"thumbnail":"https://greece-hotel.info/admins/aquavistahotels/wp-content/uploads/2022/12/Kouros-9-150x150.jpeg","thumbnail-width":150,"thumbnail-height":150,"medium":"https://greece-hotel.info/admins/aquavistahotels/wp-content/uploads/2022/12/Kouros-9-300x200.jpeg","medium-width":300,"medium-height":200,"medium_large":"https://greece-hotel.info/admins/aquavistahotels/wp-content/uploads/2022/12/Kouros-9-768x512.jpeg","medium_large-width":768,"medium_large-height":512,"large":"https://greece-hotel.info/admins/aquavistahotels/wp-content/uploads/2022/12/Kouros-9-1024x683.jpeg","large-width":1024,"large-height":683,"1536x1536":"https://greece-hotel.info/admins/aquavistahotels/wp-content/uploads/2022/12/Kouros-9-1536x1024.jpeg","1536x1536-width":1536,"1536x1536-height":1024,"2048x2048":"https://greece-hotel.info/admins/aquavistahotels/wp-content/uploads/2022/12/Kouros-9.jpeg","2048x2048-width":1920,"2048x2048-height":1280,"hotels-thumb":"https://greece-hotel.info/admins/aquavistahotels/wp-content/uploads/2022/12/Kouros-9-260x173.jpeg","hotels-thumb-width":260,"hotels-thumb-height":173}}],"intro_text":"Villa Kouros","book_now":"https://apricotandsea.reserve-online.net/","image":{"src":"https://code.rateparity.com/aquavistahotels.com/2022/12/Kouros-12.jpeg","alt":"alt image"},"excerpt":"For our visitors that prefer to enjoy the most unique and picturesque views from a little bit higher altitude than the rest, we arranged to build maisonette Kouros a little bit higher than the rest of the residences and also...","amenities":"<ul class=\"three-col\">\n<li style=\"font-weight: 400;\" aria-level=\"1\"><span style=\"font-weight: 400;\">Cleaning every day</span></li>\n<li style=\"font-weight: 400;\" aria-level=\"1\"><span style=\"font-weight: 400;\">Bed sheets change every 2 days</span></li>\n<li style=\"font-weight: 400;\" aria-level=\"1\"><span style=\"font-weight: 400;\">Free wifi</span></li>\n<li style=\"font-weight: 400;\" aria-level=\"1\"><span style=\"font-weight: 400;\">Flat-screen satellite tv</span></li>\n<li style=\"font-weight: 400;\" aria-level=\"1\"><span style=\"font-weight: 400;\">Air conditioning</span></li>\n<li style=\"font-weight: 400;\" aria-level=\"1\"><span style=\"font-weight: 400;\">Full kitchen cooking equipment</span></li>\n<li style=\"font-weight: 400;\" aria-level=\"1\"><span style=\"font-weight: 400;\">Dish washer</span></li>\n<li style=\"font-weight: 400;\" aria-level=\"1\"><span style=\"font-weight: 400;\">Oven</span></li>\n<li style=\"font-weight: 400;\" aria-level=\"1\"><span style=\"font-weight: 400;\">Microwave</span></li>\n<li style=\"font-weight: 400;\" aria-level=\"1\"><span style=\"font-weight: 400;\">Coffee machine</span></li>\n<li style=\"font-weight: 400;\" aria-level=\"1\"><span style=\"font-weight: 400;\">Fridge</span></li>\n<li style=\"font-weight: 400;\" aria-level=\"1\"><span style=\"font-weight: 400;\">Washing machine</span></li>\n<li style=\"font-weight: 400;\" aria-level=\"1\"><span style=\"font-weight: 400;\">Iron with iron board</span></li>\n<li style=\"font-weight: 400;\" aria-level=\"1\"><span style=\"font-weight: 400;\">Bathroom and pool towels</span></li>\n<li style=\"font-weight: 400;\" aria-level=\"1\"><span style=\"font-weight: 400;\">Dryer</span></li>\n<li style=\"font-weight: 400;\" aria-level=\"1\"><span style=\"font-weight: 400;\">Fireplace</span></li>\n<li style=\"font-weight: 400;\" aria-level=\"1\"><span style=\"font-weight: 400;\">Safe Box</span></li>\n<li style=\"font-weight: 400;\" aria-level=\"1\"><span style=\"font-weight: 400;\">Swimming pool</span></li>\n<li style=\"font-weight: 400;\" aria-level=\"1\"><span style=\"font-weight: 400;\">Barbecue</span></li>\n<li style=\"font-weight: 400;\" aria-level=\"1\"><span style=\"font-weight: 400;\">Outside seating space with pool and sea view</span></li>\n<li style=\"font-weight: 400;\" aria-level=\"1\"><span style=\"font-weight: 400;\">Parking</span></li>\n<li style=\"font-weight: 400;\" aria-level=\"1\"><span style=\"font-weight: 400;\">Storage space</span></li>\n</ul>\n","amenities_with_icons":[{"icon":"https://code.rateparity.com/aquavistahotels.com/2022/09/icon-3-1.svg","name":"ADSL Internet Connection"},{"icon":"https://code.rateparity.com/aquavistahotels.com/2022/07/007-fan.svg","name":"Air Conditioning"},{"icon":"https://code.rateparity.com/aquavistahotels.com/2022/07/handshake.svg","name":"Business Lounge"},{"icon":"https://code.rateparity.com/aquavistahotels.com/2022/07/bar.svg","name":"Bar"}],"gallery":["https://greece-hotel.info/admins/aquavistahotels/wp-content/uploads/2022/12/Kouros-5.jpeg","https://greece-hotel.info/admins/aquavistahotels/wp-content/uploads/2022/12/Kouros-6.jpeg","https://greece-hotel.info/admins/aquavistahotels/wp-content/uploads/2022/12/Kouros-2.jpeg","https://greece-hotel.info/admins/aquavistahotels/wp-content/uploads/2022/12/Kouros-3.jpeg","https://greece-hotel.info/admins/aquavistahotels/wp-content/uploads/2022/12/Kouros-7.jpeg","https://greece-hotel.info/admins/aquavistahotels/wp-content/uploads/2022/12/Kouros-9.jpeg","https://greece-hotel.info/admins/aquavistahotels/wp-content/uploads/2022/12/Kouros-4.jpeg","https://greece-hotel.info/admins/aquavistahotels/wp-content/uploads/2022/12/Kouros-10.jpeg","https://greece-hotel.info/admins/aquavistahotels/wp-content/uploads/2022/12/Kouros.jpeg","https://greece-hotel.info/admins/aquavistahotels/wp-content/uploads/2022/12/Kouros-8.jpeg","https://greece-hotel.info/admins/aquavistahotels/wp-content/uploads/2022/12/Kouros-12.jpeg","https://greece-hotel.info/admins/aquavistahotels/wp-content/uploads/2022/12/Kouros-11.jpeg"],"seo_title":"Villa Kouros | Rooms | Apricot & Sea Luxury Villas Naxos","seo_description":"Villa Kouros has a charming 90 sq.m interior for up to 7 guests. Double beds, large living room, direct access to swimming pool & barbecue. Book this villa now!","keywords":"","small_info":"Up to 7 Guests/ pool and sea view","link":{"pathname":"/hotels-in-naxos/apricot-sea-luxury-villas-naxos/rooms/villa-kouros","api":"/pages/room/room1","text":"Explore"}}],"css":{"title":{"element":"div","class":"post-text-body animation--up","color":"primary-dark"},"description":{"element":"div","class":"post-text-body animation--up","color":"primary-black"},"amenities":{"element":"div","class":"promo-small-text animation--up","color":"primary-black"},"link":{"element":"div","class":"button-dark","color":"primary-dark"}}}]}]},"idbName":"/undefined","schema":"schema-single-room","SEO":{"title":"Villa Portara | Rooms | Apricot & Sea Luxury Villas Naxos","description":"Villa Portara has an 85 sq.m interior for up to 7 guests, with a fully-equipped kitchen, direct access to the swimming pool & barbecue. Sea views. Book today!","keywords":""}}